{
  "date": "2026-07-24",
  "timestamp": "2026-07-24T18:54:57.717208-04:00",
  "generated_at": "2026-07-24T18:54:47.507925-04:00",
  "universe": {
    "source": "config/tickers.yaml",
    "count": 8,
    "tickers": [
      "AAPL",
      "MSFT",
      "NVDA",
      "AMD",
      "GOOGL",
      "AMZN",
      "META",
      "TSLA"
    ]
  },
  "market": {
    "ticker_count": 8,
    "sector_count": 3,
    "average_momentum_1m": 0.5249462018358049,
    "average_momentum_3m": 6.016172129057438,
    "average_momentum_6m": 11.838903518046592,
    "average_momentum_1y": 41.31197057709888,
    "average_score": 62.5,
    "news_count": 80,
    "event_count": 80
  },
  "candidates": [
    {
      "ticker": "AMD",
      "company": "Advanced Micro Devices, Inc.",
      "score": 75,
      "confidence": "High",
      "signal_strength": "Strong",
      "signal_rate": 85.35,
      "reasons": [
        "Scoring EngineのGrowthが 20/20 で、成長性の基礎条件が確認できます。",
        "Financial Healthが 20/20 で、継続調査に必要な財務基盤を評価しています。",
        "Newsスコアが 12/20 で、材料の量と市場関心を候補評価に反映しています。",
        "売上が取得でき、事業規模の確認ができます。",
        "EPSがプラスで、利益を伴う成長候補として確認できます。",
        "研究開発費が確認でき、将来成長への投資シグナルがあります。",
        "FCFがプラスで、成長投資を支える現金創出力があります。",
        "1Mモメンタムは対SPYで -0.35pt と、市場を小幅に下回っています。",
        "3Mモメンタムは対SPYで +66.38pt と、市場を大きく上回っています。",
        "6Mモメンタムは対SPYで +97.89pt と、市場を大きく上回っています。"
      ],
      "status": "Primary Candidate",
      "sector": "Technology",
      "industry": "Semiconductors",
      "metrics": {
        "scoring_total": 71.0,
        "signal_earned_points": 73.4,
        "signal_max_points": 86.0,
        "weak_signals": [],
        "scoring_signal_strength": "Strong",
        "growth_score": 20.0,
        "financial_health_score": 20.0,
        "valuation_score": 6.0,
        "news_score": 12.0,
        "momentum": {
          "1m": 0.42521684191736875,
          "3m": 70.94620088469297,
          "6m": 105.71080321441886,
          "1y": 228.99466264561732
        },
        "benchmark": "SPY",
        "excess_momentum": {
          "1m": -0.35,
          "3m": 66.38,
          "6m": 97.89,
          "1y": 211.19
        },
        "positive_news": 8,
        "watch_news": 0,
        "event_count": 10,
        "events_with_reaction": 5,
        "sector_average_score": 66.0
      },
      "evidence": [
        "Company",
        "Events",
        "Financials",
        "Knowledge",
        "Market Intelligence",
        "News",
        "Prices",
        "Scoring"
      ],
      "watch_points": [
        "バリュエーション面のスコアが低く、期待先行や割高さの確認が必要です。",
        "イベント後の平均株価反応は強くなく、材料への市場反応は確認が必要です。",
        "売上成長、営業利益率、FCFが同時に改善しているかを継続確認する必要があります。",
        "直近ニュース後の出来高と株価反応が継続的か、一時的かを確認する価値があります。",
        "Technology セクター全体の需要変化と競争環境を確認する必要があります。",
        "yfinance由来データのため、項目欠損や仕様変更の影響を受ける可能性があります。",
        "ニュースの市場反応は短期的な需給やマクロ環境にも左右されると考えられます。"
      ]
    },
    {
      "ticker": "AAPL",
      "company": "Apple Inc.",
      "score": 68,
      "confidence": "High",
      "signal_strength": "Strong",
      "signal_rate": 76.8,
      "reasons": [
        "Scoring EngineのGrowthが 17/20 で、成長性の基礎条件が確認できます。",
        "Financial Healthが 12/20 で、継続調査に必要な財務基盤を評価しています。",
        "Newsスコアが 14/20 で、材料の量と市場関心を候補評価に反映しています。",
        "売上が取得でき、事業規模の確認ができます。",
        "EPSがプラスで、利益を伴う成長候補として確認できます。",
        "研究開発費が確認でき、将来成長への投資シグナルがあります。",
        "FCFがプラスで、成長投資を支える現金創出力があります。",
        "1Mモメンタムは対SPYで +12.85pt と、市場を大きく上回っています。",
        "3Mモメンタムは対SPYで +17.33pt と、市場を大きく上回っています。",
        "6Mモメンタムは対SPYで +26.52pt と、市場を大きく上回っています。"
      ],
      "status": "Watch Candidate",
      "sector": "Technology",
      "industry": "Consumer Electronics",
      "metrics": {
        "scoring_total": 59.0,
        "signal_earned_points": 66.05,
        "signal_max_points": 86.0,
        "weak_signals": [],
        "scoring_signal_strength": "Moderate",
        "growth_score": 17.0,
        "financial_health_score": 12.0,
        "valuation_score": 3.0,
        "news_score": 14.0,
        "momentum": {
          "1m": 13.627679906951995,
          "3m": 21.905719338654375,
          "6m": 34.34213877003509,
          "1y": 56.124742713699916
        },
        "benchmark": "SPY",
        "excess_momentum": {
          "1m": 12.85,
          "3m": 17.33,
          "6m": 26.52,
          "1y": 38.32
        },
        "positive_news": 4,
        "watch_news": 3,
        "event_count": 10,
        "events_with_reaction": 3,
        "sector_average_score": 66.0
      },
      "evidence": [
        "Company",
        "Events",
        "Financials",
        "Knowledge",
        "Market Intelligence",
        "News",
        "Prices",
        "Scoring"
      ],
      "watch_points": [
        "バリュエーション面のスコアが低く、期待先行や割高さの確認が必要です。",
        "注意材料になり得るニュース表現が 3 件あります。",
        "売上成長、営業利益率、FCFが同時に改善しているかを継続確認する必要があります。",
        "直近ニュース後の出来高と株価反応が継続的か、一時的かを確認する価値があります。",
        "Technology セクター全体の需要変化と競争環境を確認する必要があります。",
        "yfinance由来データのため、項目欠損や仕様変更の影響を受ける可能性があります。",
        "ニュースの市場反応は短期的な需給やマクロ環境にも左右されると考えられます。"
      ]
    },
    {
      "ticker": "NVDA",
      "company": "NVIDIA Corporation",
      "score": 65,
      "confidence": "Medium",
      "signal_strength": "Strong",
      "signal_rate": 73.43,
      "reasons": [
        "Scoring EngineのGrowthが 20/20 で、成長性の基礎条件が確認できます。",
        "Financial Healthが 14/20 で、継続調査に必要な財務基盤を評価しています。",
        "Newsスコアが 13/20 で、材料の量と市場関心を候補評価に反映しています。",
        "売上が取得でき、事業規模の確認ができます。",
        "EPSがプラスで、利益を伴う成長候補として確認できます。",
        "研究開発費が確認でき、将来成長への投資シグナルがあります。",
        "FCFがプラスで、成長投資を支える現金創出力があります。",
        "1Mモメンタムは対SPYで +3.16pt と、市場並み以上です。",
        "3Mモメンタムは対SPYで -0.84pt と、市場を小幅に下回っています。",
        "6Mモメンタムは対SPYで +4.22pt と、市場並み以上です。"
      ],
      "status": "Watch Candidate",
      "sector": "Technology",
      "industry": "Semiconductors",
      "metrics": {
        "scoring_total": 68.0,
        "signal_earned_points": 63.15,
        "signal_max_points": 86.0,
        "weak_signals": [],
        "scoring_signal_strength": "Strong",
        "growth_score": 20.0,
        "financial_health_score": 14.0,
        "valuation_score": 11.0,
        "news_score": 13.0,
        "momentum": {
          "1m": 3.9396966522063583,
          "3m": 3.727242007729207,
          "6m": 12.038672552262337,
          "1y": 21.276195048361654
        },
        "benchmark": "SPY",
        "excess_momentum": {
          "1m": 3.16,
          "3m": -0.84,
          "6m": 4.22,
          "1y": 3.47
        },
        "positive_news": 3,
        "watch_news": 1,
        "event_count": 10,
        "events_with_reaction": 3,
        "sector_average_score": 66.0
      },
      "evidence": [
        "Company",
        "Events",
        "Financials",
        "Knowledge",
        "Market Intelligence",
        "News",
        "Prices",
        "Scoring"
      ],
      "watch_points": [
        "注意材料になり得るニュース表現が 1 件あります。",
        "イベント後の平均株価反応は強くなく、材料への市場反応は確認が必要です。",
        "売上成長、営業利益率、FCFが同時に改善しているかを継続確認する必要があります。",
        "直近ニュース後の出来高と株価反応が継続的か、一時的かを確認する価値があります。",
        "Technology セクター全体の需要変化と競争環境を確認する必要があります。",
        "yfinance由来データのため、項目欠損や仕様変更の影響を受ける可能性があります。",
        "ニュースの市場反応は短期的な需給やマクロ環境にも左右されると考えられます。"
      ]
    },
    {
      "ticker": "GOOGL",
      "company": "Alphabet Inc.",
      "score": 64,
      "confidence": "Medium",
      "signal_strength": "Strong",
      "signal_rate": 71.74,
      "reasons": [
        "Scoring EngineのGrowthが 20/20 で、成長性の基礎条件が確認できます。",
        "Financial Healthが 14/20 で、継続調査に必要な財務基盤を評価しています。",
        "Newsスコアが 15/20 で、材料の量と市場関心を候補評価に反映しています。",
        "売上が取得でき、事業規模の確認ができます。",
        "EPSがプラスで、利益を伴う成長候補として確認できます。",
        "研究開発費が確認でき、将来成長への投資シグナルがあります。",
        "FCFがプラスで、成長投資を支える現金創出力があります。",
        "1Mモメンタムは対SPYで -8.18pt と、市場を小幅に下回っています。",
        "3Mモメンタムは対SPYで -10.17pt と弱く、候補評価では注意点です。",
        "6Mモメンタムは対SPYで -10.96pt と弱く、候補評価では注意点です。"
      ],
      "status": "Watch Candidate",
      "sector": "Communication Services",
      "industry": "Internet Content & Information",
      "metrics": {
        "scoring_total": 62.0,
        "signal_earned_points": 61.7,
        "signal_max_points": 86.0,
        "weak_signals": [],
        "scoring_signal_strength": "Moderate",
        "growth_score": 20.0,
        "financial_health_score": 14.0,
        "valuation_score": 6.0,
        "news_score": 15.0,
        "momentum": {
          "1m": -7.399582286848258,
          "3m": -5.594452537407466,
          "6m": -3.1414653194853073,
          "1y": 68.56022426989612
        },
        "benchmark": "SPY",
        "excess_momentum": {
          "1m": -8.18,
          "3m": -10.17,
          "6m": -10.96,
          "1y": 50.76
        },
        "positive_news": 7,
        "watch_news": 0,
        "event_count": 10,
        "events_with_reaction": 3,
        "sector_average_score": 60.5
      },
      "evidence": [
        "Company",
        "Events",
        "Financials",
        "Knowledge",
        "Market Intelligence",
        "News",
        "Prices",
        "Scoring"
      ],
      "watch_points": [
        "バリュエーション面のスコアが低く、期待先行や割高さの確認が必要です。",
        "Communication ServicesのセクターモメンタムはWeakで、短期環境は慎重に見る必要があります。",
        "売上成長、営業利益率、FCFが同時に改善しているかを継続確認する必要があります。",
        "直近ニュース後の出来高と株価反応が継続的か、一時的かを確認する価値があります。",
        "Communication Services セクター全体の需要変化と競争環境を確認する必要があります。",
        "yfinance由来データのため、項目欠損や仕様変更の影響を受ける可能性があります。",
        "ニュースの市場反応は短期的な需給やマクロ環境にも左右されると考えられます。"
      ]
    },
    {
      "ticker": "MSFT",
      "company": "Microsoft Corporation",
      "score": 61,
      "confidence": "High",
      "signal_strength": "Strong",
      "signal_rate": 68.31,
      "reasons": [
        "Scoring EngineのGrowthが 18/20 で、成長性の基礎条件が確認できます。",
        "Financial Healthが 18/20 で、継続調査に必要な財務基盤を評価しています。",
        "Newsスコアが 15/20 で、材料の量と市場関心を候補評価に反映しています。",
        "売上が取得でき、事業規模の確認ができます。",
        "EPSがプラスで、利益を伴う成長候補として確認できます。",
        "研究開発費が確認でき、将来成長への投資シグナルがあります。",
        "FCFがプラスで、成長投資を支える現金創出力があります。",
        "1Mモメンタムは対SPYで +3.67pt と、市場並み以上です。",
        "3Mモメンタムは対SPYで -12.56pt と弱く、候補評価では注意点です。",
        "6Mモメンタムは対SPYで -22.84pt と弱く、候補評価では注意点です。"
      ],
      "status": "Watch Candidate",
      "sector": "Technology",
      "industry": "Software - Infrastructure",
      "metrics": {
        "scoring_total": 66.0,
        "signal_earned_points": 58.75,
        "signal_max_points": 86.0,
        "weak_signals": [],
        "scoring_signal_strength": "Strong",
        "growth_score": 18.0,
        "financial_health_score": 18.0,
        "valuation_score": 12.0,
        "news_score": 15.0,
        "momentum": {
          "1m": 4.443720552636576,
          "3m": -7.991163358909341,
          "6m": -15.015333874868638,
          "1y": -23.94313576174826
        },
        "benchmark": "SPY",
        "excess_momentum": {
          "1m": 3.67,
          "3m": -12.56,
          "6m": -22.84,
          "1y": -41.75
        },
        "positive_news": 5,
        "watch_news": 0,
        "event_count": 10,
        "events_with_reaction": 2,
        "sector_average_score": 66.0
      },
      "evidence": [
        "Company",
        "Events",
        "Financials",
        "Knowledge",
        "Market Intelligence",
        "News",
        "Prices",
        "Scoring"
      ],
      "watch_points": [
        "売上成長、営業利益率、FCFが同時に改善しているかを継続確認する必要があります。",
        "直近ニュース後の出来高と株価反応が継続的か、一時的かを確認する価値があります。",
        "Technology セクター全体の需要変化と競争環境を確認する必要があります。",
        "yfinance由来データのため、項目欠損や仕様変更の影響を受ける可能性があります。",
        "ニュースの市場反応は短期的な需給やマクロ環境にも左右されると考えられます。"
      ]
    }
  ]
}