{
  "ticker": "TJX",
  "company_name": "The TJX Companies, Inc.",
  "sector": "Consumer Cyclical",
  "industry": "Apparel Retail",
  "country": "United States",
  "currency": "USD",
  "exchange": "NYQ",
  "market_cap": 170367516672,
  "enterprise_value": 178150031360,
  "shares_outstanding": 1104704446,
  "beta": 0.623,
  "trailing_pe": 30.003893,
  "forward_pe": 26.778118,
  "peg_ratio": 3.28,
  "price_to_book": 16.381985,
  "eps": 5.14,
  "forward_eps": 5.75918,
  "dividend_yield": 1.24,
  "52_week_high": 170.0,
  "52_week_low": 123.78,
  "average_volume": 5925059,
  "employees": 377000,
  "website": "https://www.tjx.com",
  "business_summary": "The TJX Companies, Inc., together with its subsidiaries, operates as an off-price apparel and home fashions retailer worldwide. It operates through four segments: Marmaxx, HomeGoods, TJX Canada, and TJX International. The company provides family apparel comprising footwear; accessories, such as beauty and jewelry; home fashion products, including home basics, decorative accessories and giftware, as well as furniture, rugs, lighting, soft home, decorative accessories, tabletop, and cookware; pet and gourmet food; and other merchandise. It also offers home decor, furniture, and seasonal home merchandise. The company sells its products through stores and e-commerce sites. The TJX Companies, Inc. was incorporated in 1962 and is headquartered in Framingham, Massachusetts."
}